mkdocs_macros_test/__init__.py
mkdocs_macros_test_ntno-0.0.0.dist-info/METADATA
mkdocs_macros_test_ntno-0.0.0.dist-info/WHEEL
mkdocs_macros_test_ntno-0.0.0.dist-info/licenses/LICENSE.md
mkdocs_macros_test_ntno-0.0.0.dist-info/RECORD
