Metadata-Version: 2.1
Name: mkdocs-macros-test-ntno
Version: 0.0.0
Summary: Test macros library for macros plugin
Project-URL: Repository, https://github.com/ntno/mkdocs-macros-test.git
Author: Laurent Franceschetti
License-Expression: MIT
License-File: LICENSE.md
Keywords: documentation,mkdocs,theme
Classifier: Development Status :: 1 - Planning
Classifier: Environment :: Web Environment
Classifier: Intended Audience :: Developers
Classifier: License :: OSI Approved :: MIT License
Classifier: Programming Language :: Python
Classifier: Topic :: Documentation
Classifier: Topic :: Software Development :: Documentation
Classifier: Topic :: Text Processing :: Markup :: HTML
Requires-Python: >=3.7
